LICENSE.txt
README.md
setup.py
dtusteennl/__init__.py
dtusteennl/main_module.py
dtusteennl.egg-info/PKG-INFO
dtusteennl.egg-info/SOURCES.txt
dtusteennl.egg-info/dependency_links.txt
dtusteennl.egg-info/top_level.txt