Metadata-Version: 2.1
Name: dtusteennl
Version: 1.0
Summary: hello world
Author: steennl
License-File: LICENSE.txt
